{
    "metadata": {
        "filename": "KNI_01815",
        "category": "스포츠뉴스",
        "sub_category": 5,
        "sound": [
            2,
            4
        ],
        "quality": "HD",
        "length": 41.033,
        "format": "MP4",
        "date": "2015-09-15",
        "license": "KBS",
        "agreement_score": 3
    },
    "video": {
        "speakers_info": [
            {
                "speaker_id": "1",
                "age": "30대",
                "gender": "여성"
            }
        ],
        "term": [
            {
                "speaker_id": "1",
                "transcription": "은빛의 유선형 경기장이 웅장한 모습을 드러냅니다.",
                "sound_type": [
                    2,
                    4
                ],
                "start": 0.000,
                "end": 3.752
            },
            {
                "speaker_id": "1",
                "transcription": "국내 첫 돔 구장인 고척 스카이 돔입니다.",
                "sound_type": [
                    2,
                    4
                ],
                "start": 3.762,
                "end": 8.557
            },
            {
                "speaker_id": "1",
                "transcription": "무려 2000억 원이 투입돼 지하 2층 지상 4층 규모로 첫 삽을 뜬 지 6년 만에 완공됐습니다.",
                "sound_type": [
                    2,
                    4
                ],
                "start": 8.567,
                "end": 15.942
            },
            {
                "speaker_id": "1",
                "transcription": "그라운드에서 지붕까지는 일본 도쿄 돔보다 5미터 높은 67.5미터",
                "sound_type": [
                    2,
                    4
                ],
                "start": 15.952,
                "end": 21.989
            },
            {
                "speaker_id": "1",
                "transcription": "홈플레이트에서 담장까지는 122미터로 잠실 야구장 다음으로 깁니다.",
                "sound_type": [
                    2,
                    4
                ],
                "start": 21.999,
                "end": 28.078
            },
            {
                "speaker_id": "1",
                "transcription": "지붕에는 소음은 차단하면서 자연 채광이 들어오는 투명 차은막을 설치했습니다.",
                "sound_type": [
                    2,
                    4
                ],
                "start": 28.088,
                "end": 34.215
            },
            {
                "speaker_id": "1",
                "transcription": "쾌적하게 경기를 볼 수 있도록 여름에는 26도, 겨울에는 20도 정도로 온도가 일정하게 유지됩니다.",
                "sound_type": [
                    2
                ],
                "start": 34.225,
                "end": 41.033
            }
        ]
    },
    "summary": "기자는 국내 첫 돔 구장인 고척 스카이 돔을 소개했다.",
    "image": [
        {
            "image_info": {
                "image_id": "1",
                "image_name": "KNI_01815_01.jpg",
                "image_format": "JPG"
            },
            "image_labeling": [
                {
                    "labeling_id": "1.1",
                    "age": "30대",
                    "gender": "여성",
                    "place": 12,
                    "object": 50,
                    "act": 146
                }
            ]
        }
    ]
}