{
    "metadata": {
        "filename": "KNI_00678",
        "category": "스포츠뉴스",
        "sub_category": 17,
        "sound": [
            2,
            3
        ],
        "quality": "HD",
        "length": 22.989,
        "format": "MP4",
        "date": "2023-01-27",
        "license": "KBS",
        "agreement_score": 3
    },
    "video": {
        "speakers_info": [
            {
                "speaker_id": "1",
                "age": "30대",
                "gender": "남성"
            }
        ],
        "term": [
            {
                "speaker_id": "1",
                "transcription": "이다현은 지난해 올스타전에서 파격적인 모습으로 팬들의 시선을 사로잡았습니다.",
                "sound_type": [
                    2,
                    3
                ],
                "start": 0.000,
                "end": 6.884
            },
            {
                "speaker_id": "1",
                "transcription": "자신감 넘치는 표정에 숨겨둔 춤 솜씨를 아낌없이 뽐내 세리머니상 투표에서 압도적인 표를 받았습니다.",
                "sound_type": [
                    2,
                    3
                ],
                "start": 6.894,
                "end": 22.989
            }
        ]
    },
    "summary": "이다현은 지난해 올스타전에서 숨겨둔 춤 솜씨를 뽐내 세리머니상 투표에서 압도적인 표를 받았다.",
    "image": [
        {
            "image_info": {
                "image_id": "1",
                "image_name": "KNI_00678_01.jpg",
                "image_format": "JPG"
            },
            "image_labeling": [
                {
                    "labeling_id": "1.1",
                    "age": "20대",
                    "gender": "여성",
                    "place": 12,
                    "object": null,
                    "act": 159
                }
            ]
        }
    ]
}