{
    "metadata": {
        "filename": "KNI_00824",
        "category": "스포츠뉴스",
        "sub_category": 17,
        "sound": [
            2,
            4
        ],
        "quality": "HD",
        "length": 15.482,
        "format": "MP4",
        "date": "2023-02-15",
        "license": "KBS",
        "agreement_score": 3
    },
    "video": {
        "speakers_info": [
            {
                "speaker_id": "1",
                "age": "30대",
                "gender": "남성"
            }
        ],
        "term": [
            {
                "speaker_id": "1",
                "transcription": "시원한 후위 공격마저 성공하자 마침내 환한 미소를 되찾았습니다.",
                "sound_type": [
                    2,
                    4
                ],
                "start": 0.000,
                "end": 9.019
            },
            {
                "speaker_id": "1",
                "transcription": "평일에도 경기장을 가득 메운 팬들도 김연경을 외치며 힘을 불어넣었습니다.",
                "sound_type": [
                    2,
                    4
                ],
                "start": 9.029,
                "end": 15.482
            }
        ]
    },
    "summary": "평일에도 김연경을 외치며 팬들이 힘을 불어넣는다.",
    "image": [
        {
            "image_info": {
                "image_id": "1",
                "image_name": "KNI_00824_01.jpg",
                "image_format": "JPG"
            },
            "image_labeling": [
                {
                    "labeling_id": "1.1",
                    "age": "30대",
                    "gender": "여성",
                    "place": 12,
                    "object": null,
                    "act": 4
                }
            ]
        }
    ]
}