{
    "metadata": {
        "filename": "KNI_01393",
        "category": "스포츠뉴스",
        "sub_category": 42,
        "sound": [
            2
        ],
        "quality": "HD",
        "length": 32.042,
        "format": "MP4",
        "date": "2023-04-05",
        "license": "KBS",
        "agreement_score": 3
    },
    "video": {
        "speakers_info": [
            {
                "speaker_id": "1",
                "age": "30대",
                "gender": "남성"
            }
        ],
        "term": [
            {
                "speaker_id": "1",
                "transcription": "@이름1은 2011년 프로 축구 상무 소속으로 승부 조작에 가담해 영구 제명에 중징계를 받았습니다.",
                "sound_type": [
                    2
                ],
                "start": 0.000,
                "end": 6.488
            },
            {
                "speaker_id": "1",
                "transcription": "축구 관련 일에 종사할 수 없어 택배 배달 등 일용직 업무로 생계를 이어 왔습니다.",
                "sound_type": [
                    2
                ],
                "start": 6.498,
                "end": 12.842
            },
            {
                "speaker_id": "1",
                "transcription": "그러다 지난해부터 지인이 운영하는 경기도의 한 유소년 축구 클럽에서 버스 운전과 훈련 보조 역할을 해 왔는데 편법으로 지도자 복귀를 시도한 게 아니냐는 논란도 생겼습니다.",
                "sound_type": [
                    2
                ],
                "start": 12.852,
                "end": 24.855
            },
            {
                "speaker_id": "1",
                "transcription": "@이름1은 여론의 역풍을 맞고 철회된 지난달 28일 축구 협회의 기습 사면에 자신도 놀랐다고 말했습니다.",
                "sound_type": [
                    2
                ],
                "start": 24.865,
                "end": 32.031
            }
        ]
    },
    "summary": "@이름1은 2011년 프로 축구 상무 소속으로 승부 조작에 가담해 영구 제명에 중징계를 받았는데 지난해부터 유소년 축구 클럽에서 버스 운전과 훈련 보조 역할을 해 왔는데 편법으로 지도자 복귀를 시도한 게 아니냐는 논란도 생겼습니다.",
    "image": [
        {
            "image_info": {
                "image_id": "1",
                "image_name": "KNI_01393_01.jpg",
                "image_format": "JPG"
            },
            "image_labeling": [
                {
                    "labeling_id": "1.1",
                    "age": "30대",
                    "gender": "남성",
                    "place": 16,
                    "object": null,
                    "act": 29
                }
            ]
        }
    ]
}