{
    "metadata": {
        "filename": "MYP_04130",
        "category": "애니메이션",
        "sub_category": 4,
        "sound": [
            2,
            3
        ],
        "quality": "HD",
        "length": 16.316,
        "format": "MP4",
        "date": "2020-06-28",
        "license": "개인 방송",
        "agreement_score": 3
    },
    "video": {
        "speakers_info": [
            {
                "speaker_id": "1",
                "age": "30대",
                "gender": "남성"
            }
        ],
        "term": [
            {
                "speaker_id": "1",
                "transcription": "기름진 트바로크를 스메타나와 섞은 뒤 아니면 부드러운 코티지 치즈를 써도 되고 설탕을 넣으면 돼.",
                "sound_type": [
                    2,
                    3
                ],
                "start": 0.000,
                "end": 7.336
            },
            {
                "speaker_id": "1",
                "transcription": "그게 끝이야.",
                "sound_type": [
                    2,
                    3
                ],
                "start": 7.346,
                "end": 8.518
            },
            {
                "speaker_id": "1",
                "transcription": "그럼 지금까지 헬테이커와 함께하는 요리 시간이었어.",
                "sound_type": [
                    2,
                    3
                ],
                "start": 8.528,
                "end": 13.370
            },
            {
                "speaker_id": "1",
                "transcription": "다음에 또 보자.",
                "sound_type": [
                    2,
                    3
                ],
                "start": 13.380,
                "end": 16.316
            }
        ]
    },
    "summary": "기름진 트바로크를 스메타나와 섞은 뒤 설탕을 넣어 만든 것을 팬케이크에 넣어 먹어도 좋다.",
    "image": [
        {
            "image_info": {
                "image_id": "1",
                "image_name": "MYP_04130_01.jpg",
                "image_format": "JPG"
            },
            "image_labeling": [
                {
                    "labeling_id": "1.1",
                    "age": null,
                    "gender": null,
                    "place": 5,
                    "object": null,
                    "act": 7
                }
            ]
        }
    ]
}