{
    "metadata": {
        "filename": "MYP_02530",
        "category": "애니메이션",
        "sub_category": 4,
        "sound": [
            2,
            3,
            5
        ],
        "quality": "HD",
        "length": 78.8,
        "format": "MP4",
        "date": "2020-12-28",
        "license": "개인 방송",
        "agreement_score": 3
    },
    "video": {
        "speakers_info": [
            {
                "speaker_id": "1",
                "age": "20대",
                "gender": "남성"
            },
            {
                "speaker_id": "2",
                "age": "30대",
                "gender": "남성"
            },
            {
                "speaker_id": "3",
                "age": "50대 이상",
                "gender": "남성"
            },
            {
                "speaker_id": "4",
                "age": "20대",
                "gender": "남성"
            }
        ],
        "term": [
            {
                "speaker_id": "1",
                "transcription": "자 유로파 리그 조별 예산 5라운드 토트넘과 린츠의 경기가 펼쳐지고 있는 가운데 손흥민 선수가 시즌 12골을 기록하며 2대 1 앞서 나가고 있습니다.",
                "sound_type": [
                    2,
                    3
                ],
                "start": 0.000,
                "end": 10.379
            },
            {
                "speaker_id": "2",
                "transcription": "사실상 비기기만 해도 32강에 진출하지만 아무래도 최대한 승점을 쌓아 1위로 진출하는 게 좋겠죠?",
                "sound_type": [
                    2,
                    3
                ],
                "start": 10.389,
                "end": 16.827
            },
            {
                "speaker_id": "2",
                "transcription": "마지막까지 집중해야 합니다 토트넘.",
                "sound_type": [
                    2,
                    3
                ],
                "start": 16.837,
                "end": 18.930
            },
            {
                "speaker_id": "3",
                "transcription": "자 어느새 후반 35분이고 2대 1로 앞서고 있으니 굳히기에 들어가 볼까?",
                "sound_type": [
                    2
                ],
                "start": 18.940,
                "end": 23.088
            },
            {
                "speaker_id": "3",
                "transcription": "흥민아 교체다 알리랑 바꾸고 들어와서 쉬도록.",
                "sound_type": [
                    2,
                    3
                ],
                "start": 23.098,
                "end": 25.654
            },
            {
                "speaker_id": "4",
                "transcription": "예? 또요? 그치만 이 시간에 나가면 동점 골",
                "sound_type": [
                    2,
                    3
                ],
                "start": 25.664,
                "end": 27.977
            },
            {
                "speaker_id": "3",
                "transcription": "동점 골은 무슨 동점 골이야. 괜히 10분 더 뛰었다가 다치면 어떡하려고.",
                "sound_type": [
                    2,
                    3
                ],
                "start": 27.987,
                "end": 31.703
            },
            {
                "speaker_id": "3",
                "transcription": "다음 경기는 아스날과의 북런던 더비니까 얼른 나와서 몸 관리하고 있어.",
                "sound_type": [
                    2
                ],
                "start": 31.713,
                "end": 35.003
            },
            {
                "speaker_id": "1",
                "transcription": "자 토트넘의 무리뉴 감독 손흥민과 베일을 빼주고 알리와 오리에를 투입합니다.",
                "sound_type": [
                    2,
                    3
                ],
                "start": 35.013,
                "end": 39.044
            },
            {
                "speaker_id": "2",
                "transcription": "어? 이 시간에 손흥민 선수를 빼면 큰일 나는 거 아닙니까?",
                "sound_type": [
                    2,
                    3
                ],
                "start": 39.054,
                "end": 42.717
            },
            {
                "speaker_id": "1",
                "transcription": "예? 아이 또 그 얘기입니까?",
                "sound_type": [
                    2,
                    3
                ],
                "start": 42.727,
                "end": 44.151
            },
            {
                "speaker_id": "1",
                "transcription": "그땐 운이 좋았던 거죠. 설마 또 아 말씀드리는 순간 린츠의 요하네스 에게슈타인 기적 같은 동점 골을 만들어 냅니다.",
                "sound_type": [
                    2
                ],
                "start": 44.161,
                "end": 50.295
            },
            {
                "speaker_id": "2",
                "transcription": "제가 뭐랬어요 아스날에게 있던 만년 4등의 과학이 이제 손흥민 교체하면 실점이라는 과학으로 옮겨왔다니까요.",
                "sound_type": [
                    2,
                    3
                ],
                "start": 50.305,
                "end": 57.110
            },
            {
                "speaker_id": "1",
                "transcription": "뭘 또 그렇게까지 오버하시기는.",
                "sound_type": [
                    2
                ],
                "start": 57.120,
                "end": 58.750
            },
            {
                "speaker_id": "2",
                "transcription": "애 진짜라니까요.",
                "sound_type": [
                    2
                ],
                "start": 58.760,
                "end": 60.111
            },
            {
                "speaker_id": "1",
                "transcription": "자 린츠의 필립 바싱거가 페널티 박스에서 파울 페널티킥을 얻어낸 토트넘 델레 알리가 깔끔하게 마무리 짓습니다.",
                "sound_type": [
                    2,
                    3
                ],
                "start": 60.121,
                "end": 66.059
            },
            {
                "speaker_id": "1",
                "transcription": "3대 2 재역전",
                "sound_type": [
                    2,
                    3
                ],
                "start": 66.069,
                "end": 67.265
            },
            {
                "speaker_id": "1",
                "transcription": "이거 봐요 과학은 무슨 축구라는 게 원래 다 그런 거라고요.",
                "sound_type": [
                    2,
                    3
                ],
                "start": 67.275,
                "end": 69.879
            },
            {
                "speaker_id": "2",
                "transcription": "라고 하는 순간 린츠의 카라모코 동점 골 3대 3으로 경기 종료. 이거 봐요 제 말이 맞죠?",
                "sound_type": [
                    2,
                    3,
                    5
                ],
                "start": 69.889,
                "end": 78.800
            }
        ]
    },
    "summary": "토트넘과 린츠의 경기 중에 토트넘이 이기고 있어서 손흥민을 뺐는데 동점 골이 나와서 무승부로 경기가 끝났다.",
    "image": [
        {
            "image_info": {
                "image_id": "1",
                "image_name": "MYP_02530_01.jpg",
                "image_format": "JPG"
            },
            "image_labeling": [
                {
                    "labeling_id": "1.1",
                    "age": null,
                    "gender": null,
                    "place": 21,
                    "object": null,
                    "act": 146
                }
            ]
        }
    ]
}