{
    "metadata": {
        "filename": "MYP_02383",
        "category": "애니메이션",
        "sub_category": 4,
        "sound": [
            2,
            3
        ],
        "quality": "HD",
        "length": 74.766,
        "format": "MP4",
        "date": "2021-02-25",
        "license": "개인 방송",
        "agreement_score": 3
    },
    "video": {
        "speakers_info": [
            {
                "speaker_id": "1",
                "age": "50대 이상",
                "gender": "남성"
            },
            {
                "speaker_id": "2",
                "age": "30대",
                "gender": "남성"
            },
            {
                "speaker_id": "3",
                "age": "50대 이상",
                "gender": "남성"
            },
            {
                "speaker_id": "4",
                "age": "20대",
                "gender": "여성"
            }
        ],
        "term": [
            {
                "speaker_id": "1",
                "transcription": "뭐 어찌됐든 제일 자신 있는 메뉴가 뭐예유?",
                "sound_type": [
                    2,
                    3
                ],
                "start": 0.000,
                "end": 2.051
            },
            {
                "speaker_id": "2",
                "transcription": "예 사실 다 맛있긴 하다만 그래도 제일 기본이라면 프리메라리가 심판 아저씨에게 직접 공수한 치즈가 2장 들어간 경고 누적 버거가 시그니처입니다.",
                "sound_type": [
                    2,
                    3
                ],
                "start": 2.061,
                "end": 11.594
            },
            {
                "speaker_id": "1",
                "transcription": "경고 누적 버거 치즈가 2장이면 좀 느끼할 것 같은데",
                "sound_type": [
                    2,
                    3
                ],
                "start": 11.604,
                "end": 14.822
            },
            {
                "speaker_id": "2",
                "transcription": "그럼 치즈는 빼고 매콤 소스를 곁들인 다이렉트 퇴장 버거로 드릴까요?",
                "sound_type": [
                    2,
                    3
                ],
                "start": 14.832,
                "end": 19.149
            },
            {
                "speaker_id": "1",
                "transcription": "아니 뭐 버거 이름이 다 그 모양이에유 장사 안 되는 데는 다 이유가 있다니까 됐고 경고 누적 그걸로 가져와 봐유",
                "sound_type": [
                    2,
                    3
                ],
                "start": 19.159,
                "end": 25.245
            },
            {
                "speaker_id": "3",
                "transcription": "아 아자르 사장님 작명 센스가 영 별로인 것 같은데요 보통 치즈가 2장이면 더블 치즈 버거, 매콤한 맛이라면 스파이시 버거 이렇게 짓지 않습니까 그렇죠 보조아 씨?",
                "sound_type": [
                    2,
                    3
                ],
                "start": 25.255,
                "end": 34.649
            },
            {
                "speaker_id": "4",
                "transcription": "글쎄요 전 개성 있고 좋은데요 아무래도 SNS를 많이 하는 젊은 층을 공략하려면 메뉴의 이름도 독특해야죠",
                "sound_type": [
                    2,
                    3
                ],
                "start": 34.659,
                "end": 40.599
            },
            {
                "speaker_id": "3",
                "transcription": "아 그런가요 전 SNS라고는 네이바 뺀드 밖에 안 해 가지고요.",
                "sound_type": [
                    2,
                    3
                ],
                "start": 40.609,
                "end": 44.430
            },
            {
                "speaker_id": "4",
                "transcription": "아유 진짜 틀딱 아니랄까봐 인서타 같은 거 모르세요?",
                "sound_type": [
                    2,
                    3
                ],
                "start": 44.440,
                "end": 47.174
            },
            {
                "speaker_id": "3",
                "transcription": "우리 아들이 하던 것 같긴 한데 아무튼 말씀 드리는 순간 버거가 나왔나 봅니다.",
                "sound_type": [
                    2,
                    3
                ],
                "start": 47.184,
                "end": 51.459
            },
            {
                "speaker_id": "2",
                "transcription": "자 광고 누적 버거 나왔습니다.",
                "sound_type": [
                    2,
                    3
                ],
                "start": 51.469,
                "end": 53.920
            },
            {
                "speaker_id": "1",
                "transcription": "고생했슈 여기 두고 상황실 올라가 봐요.",
                "sound_type": [
                    2,
                    3
                ],
                "start": 53.930,
                "end": 56.245
            },
            {
                "speaker_id": "2",
                "transcription": "저기 근데 백 대표님",
                "sound_type": [
                    2,
                    3
                ],
                "start": 56.255,
                "end": 57.839
            },
            {
                "speaker_id": "1",
                "transcription": "왜유 뭐 빼먹은 거 있슈?",
                "sound_type": [
                    2,
                    3
                ],
                "start": 57.849,
                "end": 59.295
            },
            {
                "speaker_id": "2",
                "transcription": "아 제가 만든 거지만 너무 맛있어 보여서 그런데 한 입 만 먹고 올라가면 안 될까요?",
                "sound_type": [
                    2,
                    3
                ],
                "start": 59.305,
                "end": 64.195
            },
            {
                "speaker_id": "1",
                "transcription": "아 이 양반 참 웃기네 지금 농담한 거쥬?",
                "sound_type": [
                    2,
                    3
                ],
                "start": 64.205,
                "end": 67.069
            },
            {
                "speaker_id": "2",
                "transcription": "저도 농담이면 좋겠습니다 아 진짜 군침이 싹 돈다.",
                "sound_type": [
                    2,
                    3
                ],
                "start": 67.079,
                "end": 70.651
            },
            {
                "speaker_id": "1",
                "transcription": "아니 이 사람이 진짜 당장 상황실 올라가유",
                "sound_type": [
                    2,
                    3
                ],
                "start": 70.661,
                "end": 74.766
            }
        ]
    },
    "summary": "아자르가 자신의 식당 메뉴 중 제일 자신있어하는 메뉴는 프리메라리가 심판 아저씨에게 직접 공수한 치즈가 2장 들어간 경고 누적 버거입니다.",
    "image": [
        {
            "image_info": {
                "image_id": "1",
                "image_name": "MYP_02383_01.jpg",
                "image_format": "JPG"
            },
            "image_labeling": [
                {
                    "labeling_id": "1.1",
                    "age": null,
                    "gender": null,
                    "place": 21,
                    "object": null,
                    "act": 159
                }
            ]
        }
    ]
}