{
    "metadata": {
        "filename": "MYP_02948",
        "category": "애니메이션",
        "sub_category": 4,
        "sound": [
            2,
            3
        ],
        "quality": "HD",
        "length": 46.333,
        "format": "MP4",
        "date": "2020-02-26",
        "license": "개인 방송",
        "agreement_score": 3
    },
    "video": {
        "speakers_info": [
            {
                "speaker_id": "1",
                "age": "50대 이상",
                "gender": "남성"
            },
            {
                "speaker_id": "2",
                "age": "50대 이상",
                "gender": "남성"
            },
            {
                "speaker_id": "3",
                "age": "20대",
                "gender": "남성"
            },
            {
                "speaker_id": "4",
                "age": "30대",
                "gender": "남성"
            },
            {
                "speaker_id": "5",
                "age": "30대",
                "gender": "남성"
            },
            {
                "speaker_id": "6",
                "age": "50대 이상",
                "gender": "남성"
            }
        ],
        "term": [
            {
                "speaker_id": "1",
                "transcription": "2002 월드컵 이경규가 간다 간다 간다.",
                "sound_type": [
                    2,
                    3
                ],
                "start": 0.000,
                "end": 3.183
            },
            {
                "speaker_id": "1",
                "transcription": "조형기 씨 지금 전반전 내내 스페인이 너무 거칠어요.",
                "sound_type": [
                    2,
                    3
                ],
                "start": 3.193,
                "end": 6.586
            },
            {
                "speaker_id": "2",
                "transcription": "아 그러니까요.",
                "sound_type": [
                    2,
                    3
                ],
                "start": 6.596,
                "end": 8.049
            },
            {
                "speaker_id": "2",
                "transcription": "심판이 휘슬을 폼으로 들고 있는 것도 아니고",
                "sound_type": [
                    2,
                    3
                ],
                "start": 8.059,
                "end": 10.519
            },
            {
                "speaker_id": "1",
                "transcription": "스페인 선수들이 거칠게 나오니까 우리 선수들이 힘을 못 쓰고 있어요.",
                "sound_type": [
                    2,
                    3
                ],
                "start": 10.529,
                "end": 14.939
            },
            {
                "speaker_id": "1",
                "transcription": "새로 들어온 이을용 선수가 뭔가 보여줘야 해요.",
                "sound_type": [
                    2,
                    3
                ],
                "start": 14.949,
                "end": 18.129
            },
            {
                "speaker_id": "3",
                "transcription": "이거 이대로 가면 연장전까지 결판이 안 나 승부차기에 가게 될 텐데 저기 운재 형 이따가 승부차기에 가면 호아킨이",
                "sound_type": [
                    2,
                    3
                ],
                "start": 18.139,
                "end": 25.240
            },
            {
                "speaker_id": "4",
                "transcription": "박지성 무슨 벌써 승부차기까지 생각하고 있어?",
                "sound_type": [
                    2,
                    3
                ],
                "start": 25.250,
                "end": 27.396
            },
            {
                "speaker_id": "4",
                "transcription": "얼른 올라가서 공격해.",
                "sound_type": [
                    2,
                    3
                ],
                "start": 27.406,
                "end": 28.416
            },
            {
                "speaker_id": "3",
                "transcription": "아 모르겠다.",
                "sound_type": [
                    2,
                    3
                ],
                "start": 28.426,
                "end": 29.779
            },
            {
                "speaker_id": "3",
                "transcription": "일단 열심히 뛰어보자 .",
                "sound_type": [
                    2,
                    3
                ],
                "start": 29.789,
                "end": 30.941
            },
            {
                "speaker_id": "5",
                "transcription": "자 안정환이 우측에서 슛 아",
                "sound_type": [
                    2,
                    3
                ],
                "start": 30.951,
                "end": 33.601
            },
            {
                "speaker_id": "6",
                "transcription": "스페인의 역습이에요.",
                "sound_type": [
                    2,
                    3
                ],
                "start": 33.611,
                "end": 34.743
            },
            {
                "speaker_id": "6",
                "transcription": "조심해야죠.",
                "sound_type": [
                    2,
                    3
                ],
                "start": 34.753,
                "end": 35.405
            },
            {
                "speaker_id": "5",
                "transcription": "이을용이 막아섭니다.",
                "sound_type": [
                    2,
                    3
                ],
                "start": 35.415,
                "end": 36.481
            },
            {
                "speaker_id": "5",
                "transcription": "다행입니다.",
                "sound_type": [
                    2,
                    3
                ],
                "start": 36.491,
                "end": 37.133
            },
            {
                "speaker_id": "5",
                "transcription": "유상철의 기습적인 중거리 아",
                "sound_type": [
                    2,
                    3
                ],
                "start": 37.143,
                "end": 39.647
            },
            {
                "speaker_id": "6",
                "transcription": "스페인의 라울이 돌파를 시도합니다.",
                "sound_type": [
                    2,
                    3
                ],
                "start": 39.657,
                "end": 41.772
            },
            {
                "speaker_id": "5",
                "transcription": "홍명보의 정확한 태클 다행입니다.",
                "sound_type": [
                    2,
                    3
                ],
                "start": 41.782,
                "end": 46.333
            }
        ]
    },
    "summary": "박지성은 스페인이 너무 공격적이라 승부차기까지 생각하고 있다.",
    "image": [
        {
            "image_info": {
                "image_id": "1",
                "image_name": "MYP_02948_01.jpg",
                "image_format": "JPG"
            },
            "image_labeling": [
                {
                    "labeling_id": "1.1",
                    "age": null,
                    "gender": null,
                    "place": 12,
                    "object": null,
                    "act": 146
                }
            ]
        }
    ]
}