{
    "metadata": {
        "filename": "MYP_00603",
        "category": "애니메이션",
        "sub_category": 4,
        "sound": [
            2,
            3
        ],
        "quality": "HD",
        "length": 60.233,
        "format": "MP4",
        "date": "2023-02-23",
        "license": "개인 방송",
        "agreement_score": 3
    },
    "video": {
        "speakers_info": [
            {
                "speaker_id": "1",
                "age": "30대",
                "gender": "남성"
            },
            {
                "speaker_id": "2",
                "age": "40대",
                "gender": "남성"
            },
            {
                "speaker_id": "3",
                "age": "30대",
                "gender": "남성"
            },
            {
                "speaker_id": "4",
                "age": "30대",
                "gender": "남성"
            }
        ],
        "term": [
            {
                "speaker_id": "1",
                "transcription": "그럼 우린 유로파도 탈락할 빠에야 이적이라도 하라는 건가?",
                "sound_type": [
                    2,
                    3
                ],
                "start": 0.000,
                "end": 3.434
            },
            {
                "speaker_id": "1",
                "transcription": "에휴",
                "sound_type": [
                    2,
                    3
                ],
                "start": 3.444,
                "end": 3.782
            },
            {
                "speaker_id": "2",
                "transcription": "저기 손님들 식사는 맛있게 하셨습니까?",
                "sound_type": [
                    2,
                    3
                ],
                "start": 3.792,
                "end": 6.200
            },
            {
                "speaker_id": "3",
                "transcription": "아 네 뭐 직원들이 조금 이상했지만 맛은 나쁘지 않았습니다.",
                "sound_type": [
                    2,
                    3
                ],
                "start": 6.200,
                "end": 9.254
            },
            {
                "speaker_id": "2",
                "transcription": "다음엔 더 품질 높은 서비스를 약속드리겠습니다.",
                "sound_type": [
                    2,
                    3
                ],
                "start": 9.264,
                "end": 12.412
            },
            {
                "speaker_id": "2",
                "transcription": "저 계산은 어느 분이 하실 거죠?",
                "sound_type": [
                    2,
                    3
                ],
                "start": 12.422,
                "end": 14.205
            },
            {
                "speaker_id": "3",
                "transcription": "제가 할건데요.",
                "sound_type": [
                    2,
                    3
                ],
                "start": 14.205,
                "end": 15.120
            },
            {
                "speaker_id": "3",
                "transcription": "아까 여기 이 친구 얼굴에 부리또를 집어 던져서 가격을 조금 깎아주신다고 하셨었는데",
                "sound_type": [
                    2,
                    3
                ],
                "start": 15.120,
                "end": 19.401
            },
            {
                "speaker_id": "2",
                "transcription": "아 그런가요?",
                "sound_type": [
                    2,
                    3
                ],
                "start": 19.411,
                "end": 20.266
            },
            {
                "speaker_id": "2",
                "transcription": "어디 보자 프레드한테 1골, 카바니한테 1골, 막판에 그린우드한테 1골 총 3골 먹히셔서 31만 원이신데",
                "sound_type": [
                    2,
                    3
                ],
                "start": 20.276,
                "end": 26.802
            },
            {
                "speaker_id": "4",
                "transcription": "아니 지금 무슨 소릴 하시는 거예요?",
                "sound_type": [
                    2,
                    3
                ],
                "start": 26.802,
                "end": 28.392
            },
            {
                "speaker_id": "4",
                "transcription": "저흰 주방장 특선 코스로",
                "sound_type": [
                    2,
                    3
                ],
                "start": 28.392,
                "end": 29.697
            },
            {
                "speaker_id": "2",
                "transcription": "아아 제가 잠시 착각했네요.",
                "sound_type": [
                    2,
                    3
                ],
                "start": 29.707,
                "end": 31.132
            },
            {
                "speaker_id": "2",
                "transcription": "특선 코스 3인분이시면 30만 원이신데 부리또를 맞으셨다니 1인분 빼 드려서 총 20만 원이십니다.",
                "sound_type": [
                    2,
                    3
                ],
                "start": 31.130,
                "end": 36.835
            },
            {
                "speaker_id": "1",
                "transcription": "이야 이렇게 먹고 20만 원이면 저렴한데 나중에 우리 딸 데리고 한번 와야겠어",
                "sound_type": [
                    2,
                    3
                ],
                "start": 36.835,
                "end": 41.597
            },
            {
                "speaker_id": "3",
                "transcription": "야 이 바보야 우린 서비스도 받았고 흥민이 밥값도 뺀 거잖아",
                "sound_type": [
                    2,
                    3
                ],
                "start": 41.597,
                "end": 44.706
            },
            {
                "speaker_id": "1",
                "transcription": "아 그랬었지 우리 딸 데리곤 못 오겠다.",
                "sound_type": [
                    2,
                    3
                ],
                "start": 44.716,
                "end": 47.120
            },
            {
                "speaker_id": "2",
                "transcription": "저기 손님 혹시 할인 혜택에 포함되는 사항 있으신가요?",
                "sound_type": [
                    2,
                    3
                ],
                "start": 47.120,
                "end": 50.477
            },
            {
                "speaker_id": "1",
                "transcription": "할인이요?",
                "sound_type": [
                    2,
                    3
                ],
                "start": 50.477,
                "end": 51.132
            },
            {
                "speaker_id": "1",
                "transcription": "무슨 혜택이 있는데요?",
                "sound_type": [
                    2,
                    3
                ],
                "start": 51.144,
                "end": 52.325
            },
            {
                "speaker_id": "2",
                "transcription": "뭐 다양한 혜택이 있으신데요.",
                "sound_type": [
                    2,
                    3
                ],
                "start": 52.325,
                "end": 53.762
            },
            {
                "speaker_id": "2",
                "transcription": "일단 지난 시즌 리그 우승을 하셨다면 50프로 할인 그리고 유로파 우승이 30프로, 리그컵 우승이 10프로 할인되십니다.",
                "sound_type": [
                    2,
                    3
                ],
                "start": 53.762,
                "end": 60.233
            }
        ]
    },
    "summary": "화자 4는 다양한 할인 혜택이 있는데 그 중 리그 우승 50퍼센트, 유로파 우승 30퍼센트, 리그컵 우승 10퍼센트가 있다고 설명한다.",
    "image": [
        {
            "image_info": {
                "image_id": "1",
                "image_name": "MYP_00603_01.jpg",
                "image_format": "JPG"
            },
            "image_labeling": [
                {
                    "labeling_id": "1.1",
                    "age": "40대",
                    "gender": "남성",
                    "place": 2,
                    "object": null,
                    "act": 146
                }
            ]
        }
    ]
}